cluster_check/disk.py
cluster_check/metadata.py
cluster_check/xj.py
cluster_check/__init__.py
cluster_check/utils.py
cluster_check/xj_old.py
cluster_check-1.0.5.dist-info/RECORD
cluster_check-1.0.5.dist-info/metadata.json
cluster_check-1.0.5.dist-info/WHEEL
cluster_check-1.0.5.dist-info/entry_points.txt
cluster_check-1.0.5.dist-info/DESCRIPTION.rst
cluster_check-1.0.5.dist-info/top_level.txt
cluster_check-1.0.5.dist-info/METADATA
